armour/__init__.py
armour/crypt.py
armour/py.typed
armour/gen/__init__.py
armour/gen/gen.py
armour/gen/info.py
armour/gen/py.typed
armour/pdb/__init__.py
armour/pdb/entries.py
armour/pdb/exc.py
armour/pdb/header.py
armour/pdb/py.typed
armour/pdb/s.py
armour-1.3.5.dist-info/LICENSE
armour-1.3.5.dist-info/METADATA
armour-1.3.5.dist-info/WHEEL
armour-1.3.5.dist-info/top_level.txt
armour-1.3.5.dist-info/zip-safe
armour-1.3.5.dist-info/RECORD
